timy/__init__.py
timy/settings.py
timy-0.4.2.dist-info/METADATA
timy-0.4.2.dist-info/RECORD
timy-0.4.2.dist-info/WHEEL
timy-0.4.2.dist-info/top_level.txt
