Metadata-Version: 2.1
Name: timy
Version: 0.4.2
Summary: Minimalist measurement of python code time
Home-page: https://github.com/ramonsaraiva/timy
Author: Ramon Saraiva
Author-email: ramonsaraiva@gmail.com
License: MIT
Platform: UNKNOWN
